LICENSE.txt
MANIFEST.in
README.md
setup.py
blargg/__init__.py
blargg/admin.py
blargg/apps.py
blargg/feeds.py
blargg/models.py
blargg/settings.py
blargg/signals.py
blargg/sitemaps.py
blargg/urls.py
blargg/views.py
blargg/migrations/0001_initial.py
blargg/migrations/0002_auto_20181228_1711.py
blargg/migrations/0003_auto_20181228_1821.py
blargg/migrations/__init__.py
blargg/templates/blargg/entry_archive.html
blargg/templates/blargg/entry_archive_day.html
blargg/templates/blargg/entry_archive_month.html
blargg/templates/blargg/entry_archive_year.html
blargg/templates/blargg/entry_detail.html
blargg/templates/blargg/entry_list.html
blargg/templates/blargg/tag_list.html
blargg/templatetags/__init__.py
blargg/templatetags/blargg_tags.py
blargg/tests/__init__.py
blargg/tests/test_admin.py
blargg/tests/test_feeds.py
blargg/tests/test_models.py
blargg/tests/test_sitemaps.py
blargg/tests/test_views.py
blargg/tests/urls.py
django_blargg.egg-info/PKG-INFO
django_blargg.egg-info/SOURCES.txt
django_blargg.egg-info/dependency_links.txt
django_blargg.egg-info/not-zip-safe
django_blargg.egg-info/requires.txt
django_blargg.egg-info/top_level.txt